ongeza/__init__.py
ongeza/git_utils.py
ongeza/main.py
ongeza/shell_utils.py
ongeza-1.12.2.dist-info/DESCRIPTION.rst
ongeza-1.12.2.dist-info/METADATA
ongeza-1.12.2.dist-info/RECORD
ongeza-1.12.2.dist-info/WHEEL
ongeza-1.12.2.dist-info/entry_points.txt
ongeza-1.12.2.dist-info/metadata.json
ongeza-1.12.2.dist-info/top_level.txt
