Metadata-Version: 2.0
Name: ongeza
Version: 1.12.2
Summary: Your Semantic Versioning personal assistant
Home-page: https://github.com/reubano/ongeza
Author: Reuben Cummings
Author-email: reubano@gmail.com
License: MIT
Download-URL: https://github.com/reubano/ongeza/archive/v1.12.2.tar.gz
Keywords: Your,Semantic,Versioning,personal,assistant
Platform: MacOS X
Platform: Windows
Platform: Linux
Classifier: License :: OSI Approved :: MIT License
Classifier: Development Status :: 4 - Beta
Classifier: Natural Language :: English
Classifier: Programming Language :: Python :: 2
Classifier: Programming Language :: Python :: 2.7
Classifier: Programming Language :: Python :: 3
Classifier: Programming Language :: Python :: 3.4
Classifier: Programming Language :: Python :: 3.5
Classifier: Programming Language :: Python :: Implementation :: PyPy
Classifier: Environment :: Console
Classifier: Topic :: Software Development :: Libraries :: Python Modules
Classifier: Topic :: Software Development :: Version Control
Classifier: Intended Audience :: Developers
Classifier: Operating System :: POSIX :: Linux
Classifier: Operating System :: MacOS :: MacOS X
Classifier: Operating System :: Microsoft :: Windows
Requires-Dist: pkutils (>=0.12.4,<0.13.0)
Requires-Dist: pygogo (<0.9.0,>=0.8.10)
Requires-Dist: semver (<3.0.0,>=2.2.1)
Requires-Dist: future (>=0.15.2); python_version<"3.0"
